README.md
setup.py
disease_detection/__init__.py
disease_detection/cancer.py
disease_detection/diabetes.py
disease_detection/heart.py
disease_detection.egg-info/PKG-INFO
disease_detection.egg-info/SOURCES.txt
disease_detection.egg-info/dependency_links.txt
disease_detection.egg-info/requires.txt
disease_detection.egg-info/top_level.txt
disease_detection/datasets/cancer.csv
disease_detection/datasets/diabetes.csv
disease_detection/datasets/heart.csv
disease_detection/manual_disease_detection/__init__.py
disease_detection/manual_disease_detection/extractfeatures.py
disease_detection/manual_disease_detection/ml_model.py
disease_detection/manual_disease_detection/preprocess.py
disease_detection/tests/__init__.py
disease_detection/tests/test_cancer.py
disease_detection/tests/test_diabetes.py
disease_detection/tests/test_heart.py