Metadata-Version: 2.1
Name: disease-detection
Version: 0.2.3
Summary: A package for disease detection
Home-page: https://github.com/nirajprasad12/ds5010-disease-detection
Author: Niraj Prasad
Author-email: nirajsaiprasad@gmail.com
Classifier: Programming Language :: Python :: 3
Classifier: License :: OSI Approved :: MIT License
Classifier: Operating System :: OS Independent
